calc/__main__.py
space_coder_monopoly_calc-1.0.2.dist-info/METADATA
space_coder_monopoly_calc-1.0.2.dist-info/WHEEL
space_coder_monopoly_calc-1.0.2.dist-info/entry_points.txt
space_coder_monopoly_calc-1.0.2.dist-info/top_level.txt
space_coder_monopoly_calc-1.0.2.dist-info/RECORD
