Metadata-Version: 2.4
Name: space_-_coder-monopoly-calc
Version: 1.0.2
Summary: A simple calculator to keep track of you monopoly money
Author-email: Madhav Garg <gargm0325@wrdsb.ca>
Classifier: License :: OSI Approved :: MIT License
Classifier: Programming Language :: Python
Classifier: Programming Language :: Python :: 3
Requires-Python: >=3.9
Requires-Dist: tabulate
